strands_mcp_server/__init__.py
strands_mcp_server/cli.py
strands_mcp_server/mcp_client.py
strands_mcp_server/mcp_server.py
strands_mcp_server-0.1.3.dist-info/METADATA
strands_mcp_server-0.1.3.dist-info/WHEEL
strands_mcp_server-0.1.3.dist-info/entry_points.txt
strands_mcp_server-0.1.3.dist-info/licenses/LICENSE
strands_mcp_server-0.1.3.dist-info/RECORD
