Metadata-Version: 2.4
Name: strands-mcp-server
Version: 0.1.3
Summary: Transform Strands Agents into MCP servers, exposing agent tools to any MCP-compatible client
Project-URL: Homepage, https://github.com/cagataycali/strands-mcp-server
Project-URL: Documentation, https://strandsagents.com
Project-URL: Repository, https://github.com/cagataycali/strands-mcp-server
Project-URL: Issues, https://github.com/cagataycali/strands-mcp-server/issues
Author-email: Cagatay Cali <cagataycali@icloud.com>
License: MIT
License-File: LICENSE
Keywords: agents,ai,llm,mcp,model-context-protocol,strands,tools
Classifier: Development Status :: 4 - Beta
Classifier: Intended Audience :: Developers
Classifier: License :: OSI Approved :: MIT License
Classifier: Programming Language :: Python :: 3
Classifier: Programming Language :: Python :: 3.10
Classifier: Programming Language :: Python :: 3.11
Classifier: Programming Language :: Python :: 3.12
Classifier: Programming Language :: Python :: 3.13
Classifier: Topic :: Scientific/Engineering :: Artificial Intelligence
Classifier: Topic :: Software Development :: Libraries :: Python Modules
Requires-Python: >=3.10
Requires-Dist: strands-agents
Provides-Extra: dev
Requires-Dist: black>=24.0.0; extra == 'dev'
Requires-Dist: mypy>=1.11.0; extra == 'dev'
Requires-Dist: pytest-asyncio>=0.24.0; extra == 'dev'
Requires-Dist: pytest-cov>=4.1.0; extra == 'dev'
Requires-Dist: pytest>=8.0.0; extra == 'dev'
Requires-Dist: ruff>=0.6.0; extra == 'dev'
Requires-Dist: strands-agents-tools; extra == 'dev'
